golink/__init__.py
golink/cli.py
golink/script.js
golink/style.css
golink/utils.py
golink-0.5.9.dist-info/LICENSE
golink-0.5.9.dist-info/METADATA
golink-0.5.9.dist-info/WHEEL
golink-0.5.9.dist-info/entry_points.txt
golink-0.5.9.dist-info/RECORD
