Metadata-Version: 2.3
Name: golink
Version: 0.5.9
Summary: A simple URL shortener
License: GPLv3
Author: Max Vogel
Requires-Python: >=3.9,<4.0
Classifier: License :: Other/Proprietary License
Classifier: Programming Language :: Python :: 3
Classifier: Programming Language :: Python :: 3.9
Classifier: Programming Language :: Python :: 3.10
Classifier: Programming Language :: Python :: 3.11
Classifier: Programming Language :: Python :: 3.12
Classifier: Programming Language :: Python :: 3.13
Requires-Dist: docopt (>=0.6.2,<0.7.0)
Requires-Dist: gitpython (>=3.1.43,<4.0.0)
Requires-Dist: ilock (>=1.0.3,<2.0.0)
Requires-Dist: pandas (>=2.2.2,<3.0.0)
Requires-Dist: requests (>=2.31.0,<3.0.0)
Requires-Dist: tabulate (>=0.9.0,<0.10.0)
Requires-Dist: tqdm (>=4.66.4,<5.0.0)
Project-URL: Repository, https://github.com/Mehvix/golink
